cognitive_orchestra-5.0.2.dist-info/licenses/LICENSE
orchestra/__init__.py
orchestra/__main__.py
orchestra/adhd_support.py
orchestra/agent_coordinator.py
orchestra/bulkhead.py
orchestra/checkpoint.py
orchestra/claude_code_hook.py
orchestra/cognitive_orchestrator.py
orchestra/cognitive_stage.py
orchestra/cognitive_state.py
orchestra/cognitive_support.py
orchestra/cogroute_bench.py
orchestra/config.py
orchestra/convergence_tracker.py
orchestra/dashboard.py
orchestra/dashboard_bridge.py
orchestra/decision_engine.py
orchestra/expert_router.py
orchestra/fallback.py
orchestra/file_ops.py
orchestra/framework_orchestrator.py
orchestra/health.py
orchestra/http_server.py
orchestra/idempotency.py
orchestra/lifecycle.py
orchestra/logging_setup.py
orchestra/metrics.py
orchestra/otel_adapter.py
orchestra/parameter_locker.py
orchestra/prism_detector.py
orchestra/py.typed
orchestra/rate_limit.py
orchestra/research_agent.py
orchestra/resilience.py
orchestra/schemas.py
orchestra/synthesis_agent.py
orchestra/tension_surfacer.py
orchestra/tracing.py
orchestra/validation.py
orchestra/websocket_server.py
orchestra/cli/__init__.py
orchestra/cli/main.py
orchestra/cli/status.py
orchestra/cli/tui.py
orchestra/hooks/__init__.py
orchestra/hooks/__main__.py
orchestra/hooks/cognitive_hook.py
orchestra/substrate/__init__.py
orchestra/substrate/ewm/__init__.py
orchestra/substrate/ewm/manager.py
orchestra/substrate/ewm/schemas.py
orchestra/substrate/hardening/__init__.py
orchestra/substrate/hardening/handoff.py
orchestra/substrate/hardening/state_manager.py
orchestra/substrate/knowledge/__init__.py
orchestra/substrate/knowledge/retriever.py
orchestra/substrate/knowledge/schemas.py
cognitive_orchestra-5.0.2.dist-info/METADATA
cognitive_orchestra-5.0.2.dist-info/WHEEL
cognitive_orchestra-5.0.2.dist-info/entry_points.txt
cognitive_orchestra-5.0.2.dist-info/top_level.txt
cognitive_orchestra-5.0.2.dist-info/RECORD
