Metadata-Version: 2.4
Name: cognitive-orchestra
Version: 5.0.2
Summary: Cognitive orchestration system with work/delegate/protect decision model
Author: Orchestra Contributors
License: MIT
Project-URL: Homepage, https://github.com/JosephOIbrahim/Orchestra
Project-URL: Bug Tracker, https://github.com/JosephOIbrahim/Orchestra/issues
Keywords: cognitive,orchestration,agents,adhd,usd,thinkingmachines
Classifier: Development Status :: 5 - Production/Stable
Classifier: Intended Audience :: Developers
Classifier: License :: OSI Approved :: MIT License
Classifier: Operating System :: OS Independent
Classifier: Programming Language :: Python :: 3
Classifier: Programming Language :: Python :: 3.10
Classifier: Programming Language :: Python :: 3.11
Classifier: Programming Language :: Python :: 3.12
Classifier: Topic :: Software Development :: Libraries :: Python Modules
Requires-Python: >=3.10
License-File: LICENSE
Requires-Dist: aiohttp>=3.8.0
Requires-Dist: pydantic>=2.0.0
Requires-Dist: rich>=13.0.0
Provides-Extra: dev
Requires-Dist: pytest>=7.0.0; extra == "dev"
Requires-Dist: pytest-asyncio>=0.21.0; extra == "dev"
Requires-Dist: pytest-cov>=4.0.0; extra == "dev"
Requires-Dist: hypothesis>=6.100.0; extra == "dev"
Provides-Extra: tui
Requires-Dist: textual>=0.40.0; extra == "tui"
Dynamic: license-file
